<annotation>
	<folder></folder>
	<filename>1fc9a371-6bbd-4e92-b31e-4bffee712c4a-0_jpg.rf.5a9473b01bc0dff94c2909b893b849e0.jpg</filename>
	<path>1fc9a371-6bbd-4e92-b31e-4bffee712c4a-0_jpg.rf.5a9473b01bc0dff94c2909b893b849e0.jpg</path>
	<source>
		<database>roboflow.ai</database>
	</source>
	<size>
		<width>480</width>
		<height>752</height>
		<depth>3</depth>
	</size>
	<segmented>0</segmented>
	<object>
		<name>TypeWine Type</name>
		<pose>Unspecified</pose>
		<truncated>0</truncated>
		<difficult>0</difficult>
		<occluded>0</occluded>
		<bndbox>
			<xmin>389</xmin>
			<xmax>454</xmax>
			<ymin>142</ymin>
			<ymax>160</ymax>
		</bndbox>
	</object>
	<object>
		<name>TypeWine Type</name>
		<pose>Unspecified</pose>
		<truncated>0</truncated>
		<difficult>0</difficult>
		<occluded>0</occluded>
		<bndbox>
			<xmin>368</xmin>
			<xmax>461</xmax>
			<ymin>118</ymin>
			<ymax>240</ymax>
		</bndbox>
	</object>
	<object>
		<name>TypeWine Type</name>
		<pose>Unspecified</pose>
		<truncated>0</truncated>
		<difficult>0</difficult>
		<occluded>0</occluded>
		<bndbox>
			<xmin>373</xmin>
			<xmax>454</xmax>
			<ymin>174</ymin>
			<ymax>188</ymax>
		</bndbox>
	</object>
	<object>
		<name>TypeWine Type</name>
		<pose>Unspecified</pose>
		<truncated>0</truncated>
		<difficult>0</difficult>
		<occluded>0</occluded>
		<bndbox>
			<xmin>390</xmin>
			<xmax>454</xmax>
			<ymin>208</ymin>
			<ymax>220</ymax>
		</bndbox>
	</object>
	<object>
		<name>Distinct Logo</name>
		<pose>Unspecified</pose>
		<truncated>0</truncated>
		<difficult>0</difficult>
		<occluded>0</occluded>
		<bndbox>
			<xmin>67</xmin>
			<xmax>364</xmax>
			<ymin>120</ymin>
			<ymax>373</ymax>
		</bndbox>
	</object>
	<object>
		<name>Established YearYear</name>
		<pose>Unspecified</pose>
		<truncated>0</truncated>
		<difficult>0</difficult>
		<occluded>0</occluded>
		<bndbox>
			<xmin>251</xmin>
			<xmax>333</xmax>
			<ymin>22</ymin>
			<ymax>42</ymax>
		</bndbox>
	</object>
	<object>
		<name>TypeWine Type</name>
		<pose>Unspecified</pose>
		<truncated>0</truncated>
		<difficult>0</difficult>
		<occluded>0</occluded>
		<bndbox>
			<xmin>150</xmin>
			<xmax>339</xmax>
			<ymin>403</ymin>
			<ymax>433</ymax>
		</bndbox>
	</object>
	<object>
		<name>TypeWine Type</name>
		<pose>Unspecified</pose>
		<truncated>0</truncated>
		<difficult>0</difficult>
		<occluded>0</occluded>
		<bndbox>
			<xmin>157</xmin>
			<xmax>331</xmax>
			<ymin>405</ymin>
			<ymax>433</ymax>
		</bndbox>
	</object>
	<object>
		<name>Appellation AOC DOC AVARegion</name>
		<pose>Unspecified</pose>
		<truncated>0</truncated>
		<difficult>0</difficult>
		<occluded>0</occluded>
		<bndbox>
			<xmin>68</xmin>
			<xmax>197</xmax>
			<ymin>465</ymin>
			<ymax>486</ymax>
		</bndbox>
	</object>
	<object>
		<name>Maker-Name</name>
		<pose>Unspecified</pose>
		<truncated>0</truncated>
		<difficult>0</difficult>
		<occluded>0</occluded>
		<bndbox>
			<xmin>105</xmin>
			<xmax>370</xmax>
			<ymin>40</ymin>
			<ymax>92</ymax>
		</bndbox>
	</object>
</annotation>
